Workbook

Sheet Assumptions
A1: PwnIt 2 — Unit Economics Model
A2: Illustrative defaults — replace the blue cells with your own numbers. Blue = input, black = formula, green = pulled from another sheet.
A4: How the money works: with a fair 1:1 discount on a voucher sold near cost, every BUYER pays ~face value for a ~face-value voucher, so buyers fund roughly R0 of the free prize. The winner's free voucher is paid for by three things only: (1) the winner's own play spend, (2) BREAKAGE — losing players who never redeem their discount, and (3) any wholesale margin if you can source below face. Subscription revenue is a separate, stable base. So: subscription = steady margin; breakage = the variable engine; wholesale margin = the multiplier that also lets buyers become profitable.
A6: Inputs
A7: Voucher face value (V) | B7: 1000 | C7: R — what the winner wins / a buyer receives
A8: Voucher wholesale cost (C) | B8: 1000 | C8: R — your cost to source it. = face if you have no supplier deal yet
A9: Wholesale discount vs face | B9: =1-B8/B7 -> 0 | C9: Derived. >0 only once you negotiate supply below face
A10: Play price (p) | B10: 5 | C10: R per game played
A11: Players per campaign | B11: 200 | C11: Participating users in one campaign
A12: Share of players who pay | B12: 0.75 | C12: Rest play only the free daily game (R0)
A13: Avg paid plays per paying player | B13: 8 | C13: Games bought per payer over the campaign
A14: Breakage rate | B14: 0.35 | C14: Share of NON-winner paid spend that is never redeemed (lose, don't buy)
A15: Subscription price / month | B15: 49 | C15: R per subscriber per month
A16: Subscription uptake | B16: 0.05 | C16: Share of players who subscribe (stable base)
A17: Campaigns per month | B17: 4 | C17: How many campaigns you run per month

Sheet Campaign
A1: Single-Campaign P&L (current assumptions)
A3: Volume
A4: Voucher face value (V) | B4: =Assumptions!B7 -> 1000
A5: Voucher wholesale cost (C) | B5: =Assumptions!B8 -> 1000
A6: Play price (p) | B6: =Assumptions!B10 -> 5
A7: Players (participating) | B7: =Assumptions!B11 -> 200
A8: Paying players | B8: =B7*Assumptions!B12 -> 150
A9: Avg paid spend per paying player | B9: =Assumptions!B13*B6 -> 40 | C9: plays x price
A10: Total paid play revenue (P) | B10: =B8*B9 -> 6000
A11: Winner's paid spend | B11: =B9 -> 40 | C11: assume the winner spends about the average
A12: Non-winner paid spend | B12: =B10-B11 -> 5960
A13: Redeemers — buy with discount (count) | B13: =(B8-1)*(1-Assumptions!B14) -> 96.85 | C13: expected value
A14: Breakage — lose & don't buy (count) | B14: =(B8-1)*Assumptions!B14 -> 52.15 | C14: expected value
A15: Breakage revenue (forfeited play spend) | B15: =B12*Assumptions!B14 -> 2086
A17: Profit & Loss
A18: Revenue: play revenue (all players) | B18: =B10 -> 6000
A19: Revenue: purchase top-ups (redeemers) | B19: =B13*B4 - B12*(1-Assumptions!B14) -> 92976 | C19: redeemers x V, minus their own discount (their paid spend)
A20: Total revenue | B20: =B18+B19 -> 98976
A21: Less: voucher cost (winner + buyers) | B21: =-B5*(1+B13) -> -97850 | C21: C x (1 + redeemers)
A22: Campaign profit (pre-subscription) | B22: =B20+B21 -> 1126
A24: Check — shortcut formula | B24: =B11+B15+B13*(B4-B5)-B5 -> 1126 | C24: winner + breakage + buyers x (V-C) - C
A25: Check matches P&L? | B25: =IF(ROUND(B22-B24,2)=0,"yes - match","MISMATCH") -> yes - match
A27: Ratios
A28: Profit per paying player | B28: =IFERROR(B22/B8,0) -> 7.5066667
A29: Break-even breakage rate | B29: =IFERROR((B5-B11-(B8-1)*(B4-B5))/(B12-(B8-1)*(B4-B5)),"n/a") -> 0.16107383 | C29: breakage at which this campaign breaks even (most meaningful when C is near face)
A30: Read | B30: =IF(B22>=0,IF((B11+(B8-1)*(B4-B5)-B5)>=0,"Profitable even at 0% breakage","Profitable at the current breakage rate"),"Loss at the current breakage rate — needs more breakage or a supplier discount") -> Profitable at the current breakage rate

Sheet Sensitivity
A1: Campaign profit (R) by breakage x wholesale discount
A2: Rows = breakage rate. Columns = wholesale discount vs face. All other inputs from the Assumptions sheet.
A4: breakage \ wholesale disc | B4: 0 | C4: 0.05 | D4: 0.1 | E4: 0.15 | F4: 0.2
A5: 0 | B5: =(Assumptions!$B$13*Assumptions!$B$10)+(((Assumptions!$B$11*Assumptions!$B$12)*(Assumptions!$B$13*Assumptions!$B$10))-(Assumptions!$B$13*Assumptions!$B$10))*$A5+((Assumptions!$B$11*Assumptions!$B$12)-1)*(1-$A5)*(Assumptions!$B$7*B$4)-Assumptions!$B$7*(1-B$4) -> -960 | C5: =(Assumptions!$B$13*Assumptions!$B$10)+(((Assumptions!$B$11*Assumptions!$B$12)*(Assumptions!$B$13*Assumptions!$B$10))-(Assumptions!$B$13*Assumptions!$B$10))*$A5+((Assumptions!$B$11*Assumptions!$B$12)-1)*(1-$A5)*(Assumptions!$B$7*C$4)-Assumptions!$B$7*(1-C$4) -> 6540 | D5: =(Assumptions!$B$13*Assumptions!$B$10)+(((Assumptions!$B$11*Assumptions!$B$12)*(Assumptions!$B$13*Assumptions!$B$10))-(Assumptions!$B$13*Assumptions!$B$10))*$A5+((Assumptions!$B$11*Assumptions!$B$12)-1)*(1-$A5)*(Assumptions!$B$7*D$4)-Assumptions!$B$7*(1-D$4) -> 14040 | E5: =(Assumptions!$B$13*Assumptions!$B$10)+(((Assumptions!$B$11*Assumptions!$B$12)*(Assumptions!$B$13*Assumptions!$B$10))-(Assumptions!$B$13*Assumptions!$B$10))*$A5+((Assumptions!$B$11*Assumptions!$B$12)-1)*(1-$A5)*(Assumptions!$B$7*E$4)-Assumptions!$B$7*(1-E$4) -> 21540 | F5: =(Assumptions!$B$13*Assumptions!$B$10)+(((Assumptions!$B$11*Assumptions!$B$12)*(Assumptions!$B$13*Assumptions!$B$10))-(Assumptions!$B$13*Assumptions!$B$10))*$A5+((Assumptions!$B$11*Assumptions!$B$12)-1)*(1-$A5)*(Assumptions!$B$7*F$4)-Assumptions!$B$7*(1-F$4) -> 29040
A6: 0.1 | B6: =(Assumptions!$B$13*Assumptions!$B$10)+(((Assumptions!$B$11*Assumptions!$B$12)*(Assumptions!$B$13*Assumptions!$B$10))-(Assumptions!$B$13*Assumptions!$B$10))*$A6+((Assumptions!$B$11*Assumptions!$B$12)-1)*(1-$A6)*(Assumptions!$B$7*B$4)-Assumptions!$B$7*(1-B$4) -> -364 | C6: =(Assumptions!$B$13*Assumptions!$B$10)+(((Assumptions!$B$11*Assumptions!$B$12)*(Assumptions!$B$13*Assumptions!$B$10))-(Assumptions!$B$13*Assumptions!$B$10))*$A6+((Assumptions!$B$11*Assumptions!$B$12)-1)*(1-$A6)*(Assumptions!$B$7*C$4)-Assumptions!$B$7*(1-C$4) -> 6391 | D6: =(Assumptions!$B$13*Assumptions!$B$10)+(((Assumptions!$B$11*Assumptions!$B$12)*(Assumptions!$B$13*Assumptions!$B$10))-(Assumptions!$B$13*Assumptions!$B$10))*$A6+((Assumptions!$B$11*Assumptions!$B$12)-1)*(1-$A6)*(Assumptions!$B$7*D$4)-Assumptions!$B$7*(1-D$4) -> 13146 | E6: =(Assumptions!$B$13*Assumptions!$B$10)+(((Assumptions!$B$11*Assumptions!$B$12)*(Assumptions!$B$13*Assumptions!$B$10))-(Assumptions!$B$13*Assumptions!$B$10))*$A6+((Assumptions!$B$11*Assumptions!$B$12)-1)*(1-$A6)*(Assumptions!$B$7*E$4)-Assumptions!$B$7*(1-E$4) -> 19901 | F6: =(Assumptions!$B$13*Assumptions!$B$10)+(((Assumptions!$B$11*Assumptions!$B$12)*(Assumptions!$B$13*Assumptions!$B$10))-(Assumptions!$B$13*Assumptions!$B$10))*$A6+((Assumptions!$B$11*Assumptions!$B$12)-1)*(1-$A6)*(Assumptions!$B$7*F$4)-Assumptions!$B$7*(1-F$4) -> 26656
A7: 0.2 | B7: =(Assumptions!$B$13*Assumptions!$B$10)+(((Assumptions!$B$11*Assumptions!$B$12)*(Assumptions!$B$13*Assumptions!$B$10))-(Assumptions!$B$13*Assumptions!$B$10))*$A7+((Assumptions!$B$11*Assumptions!$B$12)-1)*(1-$A7)*(Assumptions!$B$7*B$4)-Assumptions!$B$7*(1-B$4) -> 232 | C7: =(Assumptions!$B$13*Assumptions!$B$10)+(((Assumptions!$B$11*Assumptions!$B$12)*(Assumptions!$B$13*Assumptions!$B$10))-(Assumptions!$B$13*Assumptions!$B$10))*$A7+((Assumptions!$B$11*Assumptions!$B$12)-1)*(1-$A7)*(Assumptions!$B$7*C$4)-Assumptions!$B$7*(1-C$4) -> 6242 | D7: =(Assumptions!$B$13*Assumptions!$B$10)+(((Assumptions!$B$11*Assumptions!$B$12)*(Assumptions!$B$13*Assumptions!$B$10))-(Assumptions!$B$13*Assumptions!$B$10))*$A7+((Assumptions!$B$11*Assumptions!$B$12)-1)*(1-$A7)*(Assumptions!$B$7*D$4)-Assumptions!$B$7*(1-D$4) -> 12252 | E7: =(Assumptions!$B$13*Assumptions!$B$10)+(((Assumptions!$B$11*Assumptions!$B$12)*(Assumptions!$B$13*Assumptions!$B$10))-(Assumptions!$B$13*Assumptions!$B$10))*$A7+((Assumptions!$B$11*Assumptions!$B$12)-1)*(1-$A7)*(Assumptions!$B$7*E$4)-Assumptions!$B$7*(1-E$4) -> 18262 | F7: =(Assumptions!$B$13*Assumptions!$B$10)+(((Assumptions!$B$11*Assumptions!$B$12)*(Assumptions!$B$13*Assumptions!$B$10))-(Assumptions!$B$13*Assumptions!$B$10))*$A7+((Assumptions!$B$11*Assumptions!$B$12)-1)*(1-$A7)*(Assumptions!$B$7*F$4)-Assumptions!$B$7*(1-F$4) -> 24272
A8: 0.3 | B8: =(Assumptions!$B$13*Assumptions!$B$10)+(((Assumptions!$B$11*Assumptions!$B$12)*(Assumptions!$B$13*Assumptions!$B$10))-(Assumptions!$B$13*Assumptions!$B$10))*$A8+((Assumptions!$B$11*Assumptions!$B$12)-1)*(1-$A8)*(Assumptions!$B$7*B$4)-Assumptions!$B$7*(1-B$4) -> 828 | C8: =(Assumptions!$B$13*Assumptions!$B$10)+(((Assumptions!$B$11*Assumptions!$B$12)*(Assumptions!$B$13*Assumptions!$B$10))-(Assumptions!$B$13*Assumptions!$B$10))*$A8+((Assumptions!$B$11*Assumptions!$B$12)-1)*(1-$A8)*(Assumptions!$B$7*C$4)-Assumptions!$B$7*(1-C$4) -> 6093 | D8: =(Assumptions!$B$13*Assumptions!$B$10)+(((Assumptions!$B$11*Assumptions!$B$12)*(Assumptions!$B$13*Assumptions!$B$10))-(Assumptions!$B$13*Assumptions!$B$10))*$A8+((Assumptions!$B$11*Assumptions!$B$12)-1)*(1-$A8)*(Assumptions!$B$7*D$4)-Assumptions!$B$7*(1-D$4) -> 11358 | E8: =(Assumptions!$B$13*Assumptions!$B$10)+(((Assumptions!$B$11*Assumptions!$B$12)*(Assumptions!$B$13*Assumptions!$B$10))-(Assumptions!$B$13*Assumptions!$B$10))*$A8+((Assumptions!$B$11*Assumptions!$B$12)-1)*(1-$A8)*(Assumptions!$B$7*E$4)-Assumptions!$B$7*(1-E$4) -> 16623 | F8: =(Assumptions!$B$13*Assumptions!$B$10)+(((Assumptions!$B$11*Assumptions!$B$12)*(Assumptions!$B$13*Assumptions!$B$10))-(Assumptions!$B$13*Assumptions!$B$10))*$A8+((Assumptions!$B$11*Assumptions!$B$12)-1)*(1-$A8)*(Assumptions!$B$7*F$4)-Assumptions!$B$7*(1-F$4) -> 21888
A9: 0.4 | B9: =(Assumptions!$B$13*Assumptions!$B$10)+(((Assumptions!$B$11*Assumptions!$B$12)*(Assumptions!$B$13*Assumptions!$B$10))-(Assumptions!$B$13*Assumptions!$B$10))*$A9+((Assumptions!$B$11*Assumptions!$B$12)-1)*(1-$A9)*(Assumptions!$B$7*B$4)-Assumptions!$B$7*(1-B$4) -> 1424 | C9: =(Assumptions!$B$13*Assumptions!$B$10)+(((Assumptions!$B$11*Assumptions!$B$12)*(Assumptions!$B$13*Assumptions!$B$10))-(Assumptions!$B$13*Assumptions!$B$10))*$A9+((Assumptions!$B$11*Assumptions!$B$12)-1)*(1-$A9)*(Assumptions!$B$7*C$4)-Assumptions!$B$7*(1-C$4) -> 5944 | D9: =(Assumptions!$B$13*Assumptions!$B$10)+(((Assumptions!$B$11*Assumptions!$B$12)*(Assumptions!$B$13*Assumptions!$B$10))-(Assumptions!$B$13*Assumptions!$B$10))*$A9+((Assumptions!$B$11*Assumptions!$B$12)-1)*(1-$A9)*(Assumptions!$B$7*D$4)-Assumptions!$B$7*(1-D$4) -> 10464 | E9: =(Assumptions!$B$13*Assumptions!$B$10)+(((Assumptions!$B$11*Assumptions!$B$12)*(Assumptions!$B$13*Assumptions!$B$10))-(Assumptions!$B$13*Assumptions!$B$10))*$A9+((Assumptions!$B$11*Assumptions!$B$12)-1)*(1-$A9)*(Assumptions!$B$7*E$4)-Assumptions!$B$7*(1-E$4) -> 14984 | F9: =(Assumptions!$B$13*Assumptions!$B$10)+(((Assumptions!$B$11*Assumptions!$B$12)*(Assumptions!$B$13*Assumptions!$B$10))-(Assumptions!$B$13*Assumptions!$B$10))*$A9+((Assumptions!$B$11*Assumptions!$B$12)-1)*(1-$A9)*(Assumptions!$B$7*F$4)-Assumptions!$B$7*(1-F$4) -> 19504
A10: 0.5 | B10: =(Assumptions!$B$13*Assumptions!$B$10)+(((Assumptions!$B$11*Assumptions!$B$12)*(Assumptions!$B$13*Assumptions!$B$10))-(Assumptions!$B$13*Assumptions!$B$10))*$A10+((Assumptions!$B$11*Assumptions!$B$12)-1)*(1-$A10)*(Assumptions!$B$7*B$4)-Assumptions!$B$7*(1-B$4) -> 2020 | C10: =(Assumptions!$B$13*Assumptions!$B$10)+(((Assumptions!$B$11*Assumptions!$B$12)*(Assumptions!$B$13*Assumptions!$B$10))-(Assumptions!$B$13*Assumptions!$B$10))*$A10+((Assumptions!$B$11*Assumptions!$B$12)-1)*(1-$A10)*(Assumptions!$B$7*C$4)-Assumptions!$B$7*(1-C$4) -> 5795 | D10: =(Assumptions!$B$13*Assumptions!$B$10)+(((Assumptions!$B$11*Assumptions!$B$12)*(Assumptions!$B$13*Assumptions!$B$10))-(Assumptions!$B$13*Assumptions!$B$10))*$A10+((Assumptions!$B$11*Assumptions!$B$12)-1)*(1-$A10)*(Assumptions!$B$7*D$4)-Assumptions!$B$7*(1-D$4) -> 9570 | E10: =(Assumptions!$B$13*Assumptions!$B$10)+(((Assumptions!$B$11*Assumptions!$B$12)*(Assumptions!$B$13*Assumptions!$B$10))-(Assumptions!$B$13*Assumptions!$B$10))*$A10+((Assumptions!$B$11*Assumptions!$B$12)-1)*(1-$A10)*(Assumptions!$B$7*E$4)-Assumptions!$B$7*(1-E$4) -> 13345 | F10: =(Assumptions!$B$13*Assumptions!$B$10)+(((Assumptions!$B$11*Assumptions!$B$12)*(Assumptions!$B$13*Assumptions!$B$10))-(Assumptions!$B$13*Assumptions!$B$10))*$A10+((Assumptions!$B$11*Assumptions!$B$12)-1)*(1-$A10)*(Assumptions!$B$7*F$4)-Assumptions!$B$7*(1-F$4) -> 17120
A11: 0.6 | B11: =(Assumptions!$B$13*Assumptions!$B$10)+(((Assumptions!$B$11*Assumptions!$B$12)*(Assumptions!$B$13*Assumptions!$B$10))-(Assumptions!$B$13*Assumptions!$B$10))*$A11+((Assumptions!$B$11*Assumptions!$B$12)-1)*(1-$A11)*(Assumptions!$B$7*B$4)-Assumptions!$B$7*(1-B$4) -> 2616 | C11: =(Assumptions!$B$13*Assumptions!$B$10)+(((Assumptions!$B$11*Assumptions!$B$12)*(Assumptions!$B$13*Assumptions!$B$10))-(Assumptions!$B$13*Assumptions!$B$10))*$A11+((Assumptions!$B$11*Assumptions!$B$12)-1)*(1-$A11)*(Assumptions!$B$7*C$4)-Assumptions!$B$7*(1-C$4) -> 5646 | D11: =(Assumptions!$B$13*Assumptions!$B$10)+(((Assumptions!$B$11*Assumptions!$B$12)*(Assumptions!$B$13*Assumptions!$B$10))-(Assumptions!$B$13*Assumptions!$B$10))*$A11+((Assumptions!$B$11*Assumptions!$B$12)-1)*(1-$A11)*(Assumptions!$B$7*D$4)-Assumptions!$B$7*(1-D$4) -> 8676 | E11: =(Assumptions!$B$13*Assumptions!$B$10)+(((Assumptions!$B$11*Assumptions!$B$12)*(Assumptions!$B$13*Assumptions!$B$10))-(Assumptions!$B$13*Assumptions!$B$10))*$A11+((Assumptions!$B$11*Assumptions!$B$12)-1)*(1-$A11)*(Assumptions!$B$7*E$4)-Assumptions!$B$7*(1-E$4) -> 11706 | F11: =(Assumptions!$B$13*Assumptions!$B$10)+(((Assumptions!$B$11*Assumptions!$B$12)*(Assumptions!$B$13*Assumptions!$B$10))-(Assumptions!$B$13*Assumptions!$B$10))*$A11+((Assumptions!$B$11*Assumptions!$B$12)-1)*(1-$A11)*(Assumptions!$B$7*F$4)-Assumptions!$B$7*(1-F$4) -> 14736
A13: Red = loss, green = profit. The current Assumptions point is shown on the Campaign sheet.

Sheet Monthly & Annual
A1: Monthly & Annual Roll-up
A4: Campaign profit (per campaign, current) | B4: =Campaign!B22 -> 1126
A5: Campaigns per month | B5: =Assumptions!B17 -> 4
A6: Campaign contribution / month | B6: =B4*B5 -> 4504 | C6: breakage-funded engine
A7: Subscribers | B7: =ROUND(Assumptions!B11*Assumptions!B16,0) -> 10 | C7: players x uptake (simplifying assumption)
A8: Subscription revenue / month | B8: =B7*Assumptions!B15 -> 490 | C8: stable recurring base
A9: Total profit / month | B9: =B6+B8 -> 4994
A10: Total profit / year | B10: =B9*12 -> 59928
A12: Note: subscription is modelled as the stable base; breakage-funded campaigns are the variable engine. A supplier discount (Assumptions C < V) adds margin on every buyer and lowers the break-even breakage rate.
